omnigrad/__init__.py
omnigrad/diffengine.py
omnigrad-0.2.3.dist-info/METADATA
omnigrad-0.2.3.dist-info/WHEEL
omnigrad-0.2.3.dist-info/top_level.txt
omnigrad-0.2.3.dist-info/RECORD
