Metadata-Version: 2.4
Name: omnigrad
Version: 0.2.3
Summary: A scalar-valued autograd engine, consider this like an extension of micrograd with support of more complex functions
Home-page: https://github.com/monkeyluffy824/omnidiff
Author: monkeyluffy824
Author-email: panangipallisaicharan@gmail.com
License: MIT
Classifier: Programming Language :: Python :: 3
Classifier: License :: OSI Approved :: MIT License
Classifier: Operating System :: OS Independent
Requires-Python: >=3.6
Dynamic: author
Dynamic: author-email
Dynamic: classifier
Dynamic: description
Dynamic: home-page
Dynamic: license
Dynamic: requires-python
Dynamic: summary
